README.txt
setup.py
simplelibs/__init__.py
simplelibs.egg-info/PKG-INFO
simplelibs.egg-info/SOURCES.txt
simplelibs.egg-info/dependency_links.txt
simplelibs.egg-info/not-zip-safe
simplelibs.egg-info/top_level.txt