Metadata-Version: 1.0
Name: simplelibs
Version: 0.1
Summary: simple libraries
Home-page: UNKNOWN
Author: Kevin S Lin
Author-email: kevinslin8@gmail.com
License: MIT
Platform: UNKNOWN
